.editorconfig
.gitignore
LICENSE
MANIFEST.in
README.rst
codecov.yml
requirements-dev.txt
setup.cfg
setup.py
tox.ini
.circleci/config.yml
girder_archive_access/__init__.py
girder_archive_access/dicom.py
girder_archive_access.egg-info/PKG-INFO
girder_archive_access.egg-info/SOURCES.txt
girder_archive_access.egg-info/dependency_links.txt
girder_archive_access.egg-info/entry_points.txt
girder_archive_access.egg-info/not-zip-safe
girder_archive_access.egg-info/requires.txt
girder_archive_access.egg-info/top_level.txt
girder_archive_access/web_client/main.js
girder_archive_access/web_client/package.json
tests/TCIA.image.tar.bz2
tests/test_archive.py