Metadata-Version: 2.1
Name: girder-archive-access
Version: 0.2.0
Summary: Access files within zip and tar archives.
Home-page: https://github.com/girder/girder_archive_access
Author: Kitware, Inc.
Author-email: kitware@kitware.com
License: Apache Software License 2.0
Keywords: girder-plugin,girder_archive_access
Platform: UNKNOWN
Classifier: Development Status :: 2 - Pre-Alpha
Classifier: License :: OSI Approved :: Apache Software License
Classifier: Natural Language :: English
Classifier: Programming Language :: Python :: 2
Classifier: Programming Language :: Python :: 2.7
Classifier: Programming Language :: Python :: 3
Classifier: Programming Language :: Python :: 3.5
Classifier: Programming Language :: Python :: 3.6
Classifier: Programming Language :: Python :: 3.7
Classifier: Programming Language :: Python :: 3.8
